{
 "1751997.0": {
  "grid": 4798,
  "name": "<b>Sylvana 5</b> <font size='-3'>(Generał Sylvana)</font>",
  "order": 20,
  "time": 1000,
  "skills": {
   "2": 3,
   "3": 2,
   "6": 3,
   "8": 3,
   "9": 3,
   "11": 3,
   "12": 3,
   "19": 1
  },
  "army": {
   "Knight": 195
  },
  "type": 57,
  "target": 799,
  "targetName": "Przywódca żeglarzy"
 },
 "555690.0": {
  "grid": 3711,
  "name": "<b>Starszy generał Gemini</b>",
  "order": 21,
  "time": 55000,
  "skills": {
   "2": 3,
   "3": 3,
   "6": 3,
   "8": 2,
   "9": 3,
   "11": 3,
   "12": 3,
   "19": 1
  },
  "army": {
   "MountedSwordsman": 26,
   "ArmoredMarksman": 269
  },
  "type": 47,
  "target": 799,
  "targetName": "Przywódca żeglarzy"
 }
}